<annotation>
	<folder></folder>
	<filename>001018_jpg.rf.3386a5314b83f9cb921ffe0f9cb8e365.jpg</filename>
	<path>001018_jpg.rf.3386a5314b83f9cb921ffe0f9cb8e365.jpg</path>
	<source>
		<database>roboflow.com</database>
	</source>
	<size>
		<width>1280</width>
		<height>720</height>
		<depth>3</depth>
	</size>
	<segmented>0</segmented>
	<object>
		<name>traffic_light</name>
		<pose>Unspecified</pose>
		<truncated>0</truncated>
		<difficult>0</difficult>
		<occluded>0</occluded>
		<bndbox>
			<xmin>428</xmin>
			<xmax>452</xmax>
			<ymin>97</ymin>
			<ymax>159</ymax>
		</bndbox>
	</object>
	<object>
		<name>traffic_light</name>
		<pose>Unspecified</pose>
		<truncated>0</truncated>
		<difficult>0</difficult>
		<occluded>0</occluded>
		<bndbox>
			<xmin>533</xmin>
			<xmax>558</xmax>
			<ymin>97</ymin>
			<ymax>159</ymax>
		</bndbox>
	</object>
	<object>
		<name>traffic_light</name>
		<pose>Unspecified</pose>
		<truncated>0</truncated>
		<difficult>0</difficult>
		<occluded>0</occluded>
		<bndbox>
			<xmin>797</xmin>
			<xmax>817</xmax>
			<ymin>148</ymin>
			<ymax>206</ymax>
		</bndbox>
	</object>
	<object>
		<name>traffic_light</name>
		<pose>Unspecified</pose>
		<truncated>0</truncated>
		<difficult>0</difficult>
		<occluded>0</occluded>
		<bndbox>
			<xmin>829</xmin>
			<xmax>850</xmax>
			<ymin>150</ymin>
			<ymax>207</ymax>
		</bndbox>
	</object>
</annotation>
