<annotation>
	<folder></folder>
	<filename>002125_jpg.rf.1ce95a423cc4329c2d93517c2eb7ff8a.jpg</filename>
	<path>002125_jpg.rf.1ce95a423cc4329c2d93517c2eb7ff8a.jpg</path>
	<source>
		<database>roboflow.com</database>
	</source>
	<size>
		<width>1280</width>
		<height>720</height>
		<depth>3</depth>
	</size>
	<segmented>0</segmented>
	<object>
		<name>traffic_light</name>
		<pose>Unspecified</pose>
		<truncated>0</truncated>
		<difficult>0</difficult>
		<occluded>0</occluded>
		<bndbox>
			<xmin>636</xmin>
			<xmax>655</xmax>
			<ymin>156</ymin>
			<ymax>180</ymax>
		</bndbox>
	</object>
	<object>
		<name>traffic_light</name>
		<pose>Unspecified</pose>
		<truncated>0</truncated>
		<difficult>0</difficult>
		<occluded>0</occluded>
		<bndbox>
			<xmin>670</xmin>
			<xmax>688</xmax>
			<ymin>152</ymin>
			<ymax>177</ymax>
		</bndbox>
	</object>
	<object>
		<name>traffic_light</name>
		<pose>Unspecified</pose>
		<truncated>0</truncated>
		<difficult>0</difficult>
		<occluded>0</occluded>
		<bndbox>
			<xmin>845</xmin>
			<xmax>863</xmax>
			<ymin>131</ymin>
			<ymax>156</ymax>
		</bndbox>
	</object>
	<object>
		<name>traffic_light</name>
		<pose>Unspecified</pose>
		<truncated>0</truncated>
		<difficult>0</difficult>
		<occluded>0</occluded>
		<bndbox>
			<xmin>876</xmin>
			<xmax>894</xmax>
			<ymin>129</ymin>
			<ymax>153</ymax>
		</bndbox>
	</object>
</annotation>
