<annotation>
	<folder></folder>
	<filename>003974_jpg.rf.6db16dd5441dd70e65aac66f88865173.jpg</filename>
	<path>003974_jpg.rf.6db16dd5441dd70e65aac66f88865173.jpg</path>
	<source>
		<database>roboflow.com</database>
	</source>
	<size>
		<width>1280</width>
		<height>720</height>
		<depth>3</depth>
	</size>
	<segmented>0</segmented>
	<object>
		<name>traffic_light</name>
		<pose>Unspecified</pose>
		<truncated>0</truncated>
		<difficult>0</difficult>
		<occluded>0</occluded>
		<bndbox>
			<xmin>666</xmin>
			<xmax>689</xmax>
			<ymin>64</ymin>
			<ymax>119</ymax>
		</bndbox>
	</object>
	<object>
		<name>traffic_light</name>
		<pose>Unspecified</pose>
		<truncated>0</truncated>
		<difficult>0</difficult>
		<occluded>0</occluded>
		<bndbox>
			<xmin>755</xmin>
			<xmax>778</xmax>
			<ymin>59</ymin>
			<ymax>115</ymax>
		</bndbox>
	</object>
	<object>
		<name>traffic_light</name>
		<pose>Unspecified</pose>
		<truncated>0</truncated>
		<difficult>0</difficult>
		<occluded>0</occluded>
		<bndbox>
			<xmin>562</xmin>
			<xmax>586</xmax>
			<ymin>70</ymin>
			<ymax>125</ymax>
		</bndbox>
	</object>
	<object>
		<name>traffic_light</name>
		<pose>Unspecified</pose>
		<truncated>0</truncated>
		<difficult>0</difficult>
		<occluded>0</occluded>
		<bndbox>
			<xmin>816</xmin>
			<xmax>837</xmax>
			<ymin>56</ymin>
			<ymax>113</ymax>
		</bndbox>
	</object>
	<object>
		<name>traffic_light</name>
		<pose>Unspecified</pose>
		<truncated>0</truncated>
		<difficult>0</difficult>
		<occluded>0</occluded>
		<bndbox>
			<xmin>892</xmin>
			<xmax>915</xmax>
			<ymin>54</ymin>
			<ymax>112</ymax>
		</bndbox>
	</object>
</annotation>
