<annotation>
	<folder></folder>
	<filename>417_1687864730091_png.rf.592acaa464d174c5ddb341fc8ac8a237.jpg</filename>
	<path>417_1687864730091_png.rf.592acaa464d174c5ddb341fc8ac8a237.jpg</path>
	<source>
		<database>roboflow.com</database>
	</source>
	<size>
		<width>1024</width>
		<height>768</height>
		<depth>3</depth>
	</size>
	<segmented>0</segmented>
	<object>
		<name>traffic_light</name>
		<pose>Unspecified</pose>
		<truncated>0</truncated>
		<difficult>0</difficult>
		<occluded>0</occluded>
		<bndbox>
			<xmin>695</xmin>
			<xmax>710</xmax>
			<ymin>241</ymin>
			<ymax>271</ymax>
		</bndbox>
	</object>
	<object>
		<name>traffic_light</name>
		<pose>Unspecified</pose>
		<truncated>0</truncated>
		<difficult>0</difficult>
		<occluded>0</occluded>
		<bndbox>
			<xmin>658</xmin>
			<xmax>668</xmax>
			<ymin>272</ymin>
			<ymax>295</ymax>
		</bndbox>
	</object>
	<object>
		<name>traffic_light</name>
		<pose>Unspecified</pose>
		<truncated>0</truncated>
		<difficult>0</difficult>
		<occluded>0</occluded>
		<bndbox>
			<xmin>281</xmin>
			<xmax>292</xmax>
			<ymin>288</ymin>
			<ymax>310</ymax>
		</bndbox>
	</object>
	<object>
		<name>traffic_light</name>
		<pose>Unspecified</pose>
		<truncated>0</truncated>
		<difficult>0</difficult>
		<occluded>0</occluded>
		<bndbox>
			<xmin>318</xmin>
			<xmax>330</xmax>
			<ymin>305</ymin>
			<ymax>325</ymax>
		</bndbox>
	</object>
	<object>
		<name>traffic_light</name>
		<pose>Unspecified</pose>
		<truncated>0</truncated>
		<difficult>0</difficult>
		<occluded>0</occluded>
		<bndbox>
			<xmin>343</xmin>
			<xmax>352</xmax>
			<ymin>313</ymin>
			<ymax>333</ymax>
		</bndbox>
	</object>
	<object>
		<name>traffic_light</name>
		<pose>Unspecified</pose>
		<truncated>0</truncated>
		<difficult>0</difficult>
		<occluded>0</occluded>
		<bndbox>
			<xmin>479</xmin>
			<xmax>484</xmax>
			<ymin>327</ymin>
			<ymax>339</ymax>
		</bndbox>
	</object>
	<object>
		<name>traffic_light</name>
		<pose>Unspecified</pose>
		<truncated>0</truncated>
		<difficult>0</difficult>
		<occluded>0</occluded>
		<bndbox>
			<xmin>516</xmin>
			<xmax>522</xmax>
			<ymin>327</ymin>
			<ymax>341</ymax>
		</bndbox>
	</object>
</annotation>
